{
  "version": 3,
  "middleware": {
    "/": {
      "files": [
        "prerender-manifest.js",
        "server/edge-runtime-webpack.js",
        "server/src/middleware.js"
      ],
      "name": "src/middleware",
      "page": "/",
      "matchers": [
        {
          "regexp": "^(?:\\/(_next\\/data\\/[^/]{1,}))?(?:\\/((?!api|_next\\/static|_next\\/image|.*\\..*|payment\\/success).*))(.json)?[\\/#\\?]?$",
          "originalSource": "/((?!api|_next/static|_next/image|.*\\..*|payment/success).*)"
        }
      ],
      "wasm": [],
      "assets": [],
      "environments": {
        "previewModeId": "77975bf9741adc47f11f79fdc8de8859",
        "previewModeSigningKey": "0d12ec204a941964991801b22bf81d96d1134410441f49ffc3eabef63954ed8b",
        "previewModeEncryptionKey": "03d3ad0700f9f5a513bfdc1a223aee20e5bc5804fac6c0c9f6abb05005d9929f"
      }
    }
  },
  "functions": {},
  "sortedMiddleware": [
    "/"
  ]
}